<?xml version="1.0" encoding="UTF-8"?>
<databaseChangeLog 
  xmlns="http://www.liquibase.org/xml/ns/dbchangelog"
  xmlns:xsi="http://www.w3.org/2001/XMLSchema-instance" xmlns:ext="http://www.liquibase.org/xml/ns/dbchangelog-ext"
  xsi:schemaLocation="http://www.liquibase.org/xml/ns/dbchangelog http://www.liquibase.org/xml/ns/dbchangelog/dbchangelog-3.1.xsd
        http://www.liquibase.org/xml/ns/dbchangelog-ext http://www.liquibase.org/xml/ns/dbchangelog/dbchangelog-ext.xsd">

  <changeSet author="vgaikwad" id="Delete two lines if row contains biospy number" dbms="mysql">
    <sql>
      update 
        catissue_deidentified_text 
      set 
        delete_next_line = 1 
      where 
        string_content= 'Biopsy No';
    </sql>
  </changeSet>
  
  <changeSet author="vgaikwad" id="Delete unused row from deidentification text table " dbms="mysql">
    <sql>
      delete from catissue_deidentified_text where string_content= 'Primary Provider:';
    </sql>
  </changeSet>
  
  <changeSet author="vgaikwad" id="Added token to remove hospital name from header" dbms="mysql">
    <sql>
      insert into catissue_deidentified_text
        (string_content, delete_line, delete_next_line) 
      values
        ('KK Hospital', 1, 0);
    </sql>
  </changeSet>
  
  <changeSet author="vgaikwad" id="Delete unused token 'Histopathology Report Final' from deidentification text table " dbms="mysql">
    <sql>
      delete from catissue_deidentified_text where string_content= 'Histopathology Report Final';
    </sql>
  </changeSet>
  
  <changeSet author="vgaikwad" id="Added token to remove Date and 'Histopathology Report' text from header of spr" dbms="mysql">
    <sql>
      insert into catissue_deidentified_text
        (string_content, delete_line, delete_next_line) 
      values 
        ('\\b\\d{1,2}-[a-zA-Z]{3}-\\d{4} \\d{2}:\\d{2}\\b Histopathology Report', 1, 0);
    </sql>
  </changeSet>
  
  <changeSet author="vgaikwad" id="Added regular expressions for date formats dd-mm-yyyy and dd-mmm-yyyy to deidentify dates in spr report" dbms="mysql">
    <sql>
      insert into catissue_deidentified_text
        (string_content, delete_line, delete_next_line) 
      values
        ("\\d{1,2}/\\d{1,2}/\\d{4} \\d{4}\\b", 0, 0);
        
      insert into catissue_deidentified_text
        (string_content, delete_line, delete_next_line) 
      values
        ("\\b\\d{1,2}-[a-zA-Z]{3}-\\d{4}", 0, 0);   
    </sql>
  </changeSet>
  
  <changeSet author="nmarwaha" id="Migrate SCG Missed case data" failOnError="false">
    <sql>
      update
        catissue_specimen_coll_group
      set
        REASON_FOR_MISSED_CASE = 'No post ops consent taken within 3 months'
      where
        collection_status = 'Not Collected-No post ops consent taken within three months'
    </sql>
    
    <sql>
      update
        catissue_specimen_coll_group
      set
        REASON_FOR_MISSED_CASE = 'No post ops consent taken within 3 months'
      where
        REASON_FOR_MISSED_CASE = 'No Post Ops consent taken within 3 mths'
    </sql>
    
    <sql>
      update
        catissue_specimen_coll_group
      set
        MISSED_REASON = REASON_FOR_MISSED_CASE
    </sql>
    
    <sql>
      update
        catissue_specimen_coll_group
      set
        COLLECTION_STATUS = 'Complete'
      where
        COLLECTION_STATUS = 'Complete-Late'
    </sql>
    
    <sql>
      update
        catissue_specimen_coll_group
      set
        COLLECTION_STATUS = 'Missed Collection'
      where
        COLLECTION_STATUS not in ('Pending', 'Complete')
    </sql>
  </changeSet>
  
  <changeSet author="nmarwaha" id="Drop older reason for missed case column from SCG table">
    <dropColumn
      tableName="CATISSUE_SPECIMEN_COLL_GROUP"
      columnName="REASON_FOR_MISSED_CASE"/>    
  </changeSet>
  
  <changeSet author="nmarwaha" id="Set label formats for all protocols as per SG format" runOnChange="true">
    <sql>
      update
        catissue_collection_protocol
      set
        LABEL_FORMAT='%VISIT_NAME%-%SP_TYPE%%PPI_SPEC_TYPE_UID%-%SP_PATH_STATUS%',
        DERIV_LABEL_FORMAT='%PSPEC_LABEL%-%SP_TYPE%',
        ALIQUOT_LABEL_FORMAT='%PSPEC_LABEL%_%PSPEC_UID%'
    </sql>
  </changeSet>
  
  <changeSet author="nmarwaha" id="Reset TRID counter in key sequence table">
    <sql>
      select 
        MAX(CAST(SUBSTRING(name, 2, length(name)) AS UNSIGNED)) 
      from 
        catissue_specimen_coll_group 
      where 
        name like 'z%'
      into 
        @TRID_FLAG;

      insert into key_seq_generator 
        (identifier, key_value, key_sequence_id, key_type)
      values 
        (default, 'SGH', @TRID_FLAG ,'TRID');
    </sql>
  </changeSet>
  
  <changeSet author="nmarwaha" id="Updating default site for CPE from CP">
    <sql>
      update 
        catissue_coll_prot_event cpe
        join catissue_site_cp site_cp on site_cp.collection_protocol_id = cpe.collection_protocol_id
      set 
        cpe.default_site_id = site_cp.site_id
      where 
        cpe.default_site_id is null
    </sql>
  </changeSet>
  
  <changeSet author="nmarwaha" id="Adding SGH specific configuration parameters">
    <sql>
      insert into os_modules
        (identifier, name, description)
      values 
        (default, 'plugin_sgh', 'SGH custom module plugin');
    </sql>
    
    <sql>
      call add_cfg_prop(
        'plugin_sgh', 'copies_to_print', 
        'copies_to_print', 'copies_to_print_desc', 
        'STRING', ''
      );
    </sql>
    
    <sql>
      call add_cfg_prop(
        'plugin_sgh', 'trid_copies', 
        'trid_copies', 'trid_copies_desc', 
        'STRING', ''
      );
    </sql>
    
    <sql>
      call add_cfg_prop(
        'plugin_sgh', 'malignant_aliq_cnt', 
        'malignant_aliq_cnt', 'malignant_aliq_cnt_desc', 
        'STRING', ''
      );
    </sql>
    
    <sql>
      call add_cfg_prop(
        'plugin_sgh', 'non_malignant_aliq_cnt', 
        'non_malignant_aliq_cnt', 'non_malignant_aliq_cnt_desc', 
        'STRING', ''
      );
    </sql>
    
    <sql>
      call add_cfg_prop(
        'plugin_sgh', 'malignant_aliq_suffix', 
        'malignant_aliq_suffix', 'malignant_aliq_suffix_desc', 
        'STRING', ''
      );
    </sql>
    
    <sql>
      call add_cfg_prop(
        'plugin_sgh', 'non_malignant_aliq_suffix', 
        'non_malignant_aliq_suffix', 'non_malignant_aliq_suffix_desc', 
        'STRING', ''
      );
    </sql>
  </changeSet>
  <changeSet author="vratnaparkhi" id="Setting parent and derivate specimen storage requirement to Virtual">
    <sql>
      update
        catissue_cp_req_specimen
      set
        storage_type = 'Virtual'
      where lineage in('New', 'Derived');
    </sql>
  </changeSet>
  
  <changeSet author="vratnaparkhi" id="Updating initial quantity to non-zero in specimen requirements">
    <loadUpdateData
      file="com/krishagni/openspecimen/sgh/specimen_req_initial_quantity.csv"
      primaryKey="identifier"
      tableName="catissue_cp_req_specimen">
      <column name="initial_quantity" type="numeric"/>
    </loadUpdateData>
  </changeSet>
  
  <changeSet author="hemant" id="Updating collection event table from scg event">
    <sql>
      update
        catissue_coll_event_param cscep
        inner join catissue_specimen cs on cs.identifier=cscep.specimen_id
        inner join catissue_specimen_coll_group scg on cs.specimen_collection_group_id=scg.identifier
      set 
        cscep.user_id=scg.collector_id,
        cscep.container=scg.collection_container, 
        cscep.collection_procedure=scg.collection_procedure, 
        cscep.comments=scg.collection_comments,
        cscep.event_timestamp=scg.collection_timestamp 
      where 
        cs.collection_status='Collected'
        and cs.lineage='New'
        and cs.activity_status != 'Disabled'
        and scg.collection_container != 'Use CP Defaults'
        and scg.collection_procedure != 'Use CP Defaults';
    </sql>
  </changeSet>

  <changeSet author="hemant" id="Updating received event table from scg event">
    <sql>
      update
        catissue_received_event_param crep
        inner join catissue_specimen cs on cs.identifier=crep.specimen_id
        inner join catissue_specimen_coll_group scg on cs.specimen_collection_group_id=scg.identifier
      set 
        crep.user_id=scg.receiver_id,
        crep.comments=scg.received_comments, 
        crep.event_timestamp=scg.received_timestamp, 
        crep.received_quality=scg.received_quality
      where 
        cs.collection_status='Collected'
        and cs.lineage='New'
        and cs.activity_status != 'Disabled'
        and scg.received_quality != 'Use CP Defaults';
    </sql>
   </changeSet>
 
  <changeSet author="hemant" id="Updating container column of collection event table">
    <sql>
      update
        catissue_coll_event_param cscep
        inner join catissue_specimen cs on cs.identifier=cscep.specimen_id
        inner join catissue_cp_req_specimen as ccrs on ccrs.identifier= cs.req_specimen_id
        join catissue_specimen_coll_group scg on  cs.specimen_collection_group_id=scg.identifier
      set 
        cscep.container=ccrs.collection_container 
      where 
        cs.collection_status='Collected'
        and cs.lineage='New'
        and cs.activity_status != 'Disabled'
        and scg.collection_container='Use CP Defaults';
    </sql>
  </changeSet>

  <changeSet author="hemant" id="Updating collection procedure column of collection event table">
    <sql>
      update
        catissue_coll_event_param cscep
        inner join catissue_specimen cs on cs.identifier=cscep.specimen_id
        inner join catissue_cp_req_specimen as ccrs on ccrs.identifier= cs.req_specimen_id
        join catissue_specimen_coll_group scg on  cs.specimen_collection_group_id=scg.identifier
      set 
        cscep.collection_procedure=ccrs.collection_procedure  
      where 
        cs.collection_status='Collected'
        and cs.lineage='New'
        and cs.activity_status != 'Disabled'
        and scg.collection_procedure='Use CP Defaults';
    </sql>
  </changeSet>
   
  <changeSet author="hemant" id="Updating received quality column of received event table">
    <sql>
      update
        catissue_received_event_param crep
        inner join catissue_specimen cs on cs.identifier=crep.specimen_id
        inner join catissue_cp_req_specimen as ccrs on ccrs.identifier= cs.req_specimen_id
        join catissue_specimen_coll_group scg on  cs.specimen_collection_group_id=scg.identifier
      set 
        crep.received_quality=ccrs.received_quality 
      where 
        cs.collection_status='Collected'
        and cs.lineage='New'
        and cs.activity_status != 'Disabled'
        and scg.received_quality='Use CP Defaults';
    </sql>
  </changeSet>
  
  <changeSet author="nmarwaha" id="Set allowed manual visit name falg to true">
    <sql>
      update 
        catissue_collection_protocol 
      set 
        MANUAL_VISIT_NAME_ALLOWED=1 
      where 
        identifier in (
          select 
            collection_protocol_id 
          from 
            catissue_site_cp site_cp
            join catissue_site site on site.identifier=site_cp.site_id 
          where 
            name='TissueBank');
    </sql>
  </changeSet>
  
  <changeSet author="nmarwaha" id="Delete the newly added missed collection status values">
    <sql>
      delete from
        catissue_permissible_value
      where 
        public_id = 'missed_visit_reason'
    </sql>
  </changeSet>
  
  <changeSet author="nmarwaha" id="Update the publuc ID of the older missed collection statuc values">
    <sql>
      update
        catissue_permissible_value
      set 
        public_id = 'missed_visit_reason'
      where 
        public_id = '2004301'
    </sql>
  </changeSet>
  
  <changeSet author="nmarwaha" id="Setting the default distribution site for the DP">
    <sql>
      insert into os_distribution_protocol_sites 
        (
        select 
          dp.identifier, site.identifier 
        from 
          catissue_distribution_protocol dp, 
          catissue_site site
        where 
          site.name in ('Biospecimen','TissueBank')
        )
    </sql>
  </changeSet>

  <changeSet author="nmarwaha" id="Setting the bulk registration workflow for the CPs with site 'Biospecimen'">
    <sql>
      insert into os_cp_workflows
        (
        select 
          site_cp.collection_protocol_id , '[{"name": "bulkRegister","data": {"enabled": true}}]' 
        from 
          catissue_site_cp site_cp 
          join catissue_site site on site_cp.site_id = site.identifier 
        where 
          site.name = 'Biospecimen'
        )
    </sql>
  </changeSet>
  
  <changeSet author="nmarwaha" id="Set the NRIC validation pattern">
    <sql>
      select 
        identifier into @module_id 
      from 
        os_modules 
      where 
        name = 'biospecimen';

      select 
        identifier into @prop_id 
      from 
        os_cfg_props 
      where 
        name = 'participant_uid_pattern' and module_id = @module_id;
        
      update 
        os_cfg_settings
      set 
        value = '^((S|T|F|G)[0-9]{7}|(X|Y)[0-9]{10})[a-zA-Z]$'
      where 
        property_id = @prop_id 

    </sql>
  </changeSet>
  
  <changeSet author="nmarwaha" id="Disable the return event form, which got loaded during 1.1 upgrade">
    <sql>
      update
        dyextn_containers
      set
        deleted_on = now()
      where 
        name = 'SpecimenReturnEvent';
    </sql>
    
    <sql>
      update 
        catissue_form_context ctxt
        join dyextn_containers de on de.identifier = ctxt.container_id
      set
        ctxt.deleted_on = now()
      where 
        de.name = 'SpecimenReturnEvent';
    </sql>
  </changeSet>
  
  <changeSet author="nmarwaha" id="Set the NRIC mandatory flag to true">
    <sql>
      select 
        identifier into @module_id 
      from 
        os_modules 
      where 
        name = 'biospecimen';

      select 
        identifier into @prop_id 
      from 
        os_cfg_props 
      where 
        name = 'uid_mandatory' and module_id = @module_id;
        
      update 
        os_cfg_settings
      set 
        value = 'true'
      where 
        property_id = @prop_id 
    </sql>
  </changeSet>
  
  <changeSet author="nmarwaha" id="Disable all the default queries">
    <sql>
      update catissue_saved_queries set deleted_on = now();
    </sql>
  </changeSet>
  
  <changeSet author="nmarwaha" id="Set consent waived option to 1 as SG is not using consent feature at CP level">
    <sql>
      update catissue_collection_protocol set consents_waived=1;
    </sql>
  </changeSet>
  
  <changeSet author="nmarwaha" id="Set the SGH specific report identifier">
    <sql>
      select 
        identifier into @module_id 
      from 
        os_modules 
      where 
        name = 'biospecimen';

      select 
        identifier into @prop_id 
      from 
        os_cfg_props 
      where 
        name = 'spr_deidentifier' and module_id = @module_id;
        
      update 
        os_cfg_settings
      set 
        value = 'sghReportsDeIdentifier'
      where 
        property_id = @prop_id
    </sql>
  </changeSet>

  <changeSet author="hkambale" id="Removed Cellular Pellet specimen type from class Cell">
    <sql>
      delete from 
        catissue_permissible_value 
      where 
        value = 'Cellular Pellet'
    </sql>
  </changeSet>

  <changeSet author="hkambale" id="Added Cellular Pellet specimen type under class Fluid">
    <preConditions onFail="MARK_RAN">
      <sqlCheck expectedResult="0">
        select
          count(pv.identifier)
        from
          catissue_permissible_value pv
          join catissue_permissible_value parent on pv.parent_identifier = parent.identifier
        where
          pv.value = 'Cellular Pellet' and parent.value = 'Fluid' and parent.public_id = '2003991'
      </sqlCheck>
    </preConditions>
    <sql>
      insert into catissue_permissible_value
        (identifier, concept_code, definition, parent_identifier, value, public_id, sortorder)
      values
        (getNextPvId(),'','',getPvParentId('2003991', 'Fluid'),'Cellular Pellet',null,null)
    </sql>
  </changeSet>

  <changeSet author="nmarwaha" id="Set specimen type abbreviation for specimen labels">
    <sql>
      select 
        identifier into @module_id 
      from 
        os_modules 
      where 
        name = 'biospecimen';

      select 
        identifier into @prop_id 
      from 
        os_cfg_props 
      where 
        name = 'specimen_type_abbr_map' and module_id = @module_id;
        
      update 
        os_cfg_settings
      set 
        value = 'classpath:/com/krishagni/openspecimen/sgh/specimen_type_abbre.csv'
      where 
        property_id = @prop_id
    </sql>
  </changeSet>
  
  <changeSet author="nmarwaha" id="Updating quantity units for the specimen type and class">
    <sql>
      update os_specimen_units set qty_unit='ml/Test tubes' where specimen_class='Fluid';
    </sql>
    
    <sql>
      update os_specimen_units set qty_unit='cell count' where specimen_class='Cell';
    </sql>
    
    <sql>
      update os_specimen_units set qty_unit='gm/Bites' where specimen_class='Tissue';
    </sql>
    <sql>
      insert into os_specimen_units
        (specimen_class, specimen_type, qty_unit, qty_html_display_code, activity_status)
      values
        ("Tissue", "Frozen Tissue Slide", "count", NULL, "Active"),
        ("Tissue", "Fixed Tissue Block", "count", NULL, "Active"),
        ("Tissue", "Frozen Tissue Block", "count", NULL, "Active"),
        ("Tissue", "Fixed Tissue Slide", "count", NULL, "Active"),
        ("Tissue", "Microdissected", "cells", NULL, "Active")
    </sql>
  </changeSet>

  <changeSet author="nmarwaha" id="Set the pathology abbreviation file for SGH">
    <sql>
      select 
        identifier into @module_id 
      from 
        os_modules 
      where 
        name = 'biospecimen';

      select 
        identifier into @prop_id 
      from 
        os_cfg_props 
      where 
        name = 'spmn_path_status_abbr_map' and module_id = @module_id;
        
      update 
        os_cfg_settings
      set 
        value = 'classpath:/com/krishagni/openspecimen/sgh/spmn_path_status.csv'
      where 
        property_id = @prop_id
    </sql>
  </changeSet>
  
  <changeSet author="nmarwaha" id="Updating the sequence values for parent specimen unique id for aliquots">
    <sql>
      delete from
        key_seq_generator
      where
        key_type = 'PSPEC_UID'; 
    </sql>
    <sql endDelimiter="//">
      drop procedure if exists updatePspecUid //

      create procedure updatePspecUid ()

      begin
        declare parentId bigint;
        declare aliqCount bigint;
        declare v_finished INTEGER DEFAULT 0;

        declare curs cursor for 
          select 
            parent_specimen_id 
          from 
            catissue_specimen 
          where 
            parent_specimen_id is not null and lineage='Aliquot' group by parent_specimen_id;

        declare continue handler 
          for not found set v_finished = 1;

        Open curs;
        get_aliq_cnt: loop
          fetch curs into parentId;

          if v_finished = 1 then 
            leave get_aliq_cnt;
          end if;

          select 
            count(*) into aliqCount 
          from 
            catissue_specimen 
          where 
            parent_specimen_id = parentId and lineage = 'Aliquot' and label is not null;
      
          if(aliqCount > 0) then
            insert into key_seq_generator(key_value, key_sequence_id, key_type)
            values(parentId,aliqCount,'PSPEC_UID');
          end if;

        end loop get_aliq_cnt;
        close curs;

      end
      //
    </sql>
    
    <sql>call updatePspecUid();</sql>
  </changeSet>

  <changeSet author="vlonushte" id="Creating specimen collection event param view">
    <createView viewName="os_cep_records_view">
      select
        re.object_id as specimen_id, cep.identifier as identifier, cep.collection_procedure, 
        cep.container as container, cep.event_timestamp as event_timestamp, cep.user_id as user_id, 
        cep.comments as comments
      from
        dyextn_containers dc 
        join catissue_form_context fc on fc.container_id = dc.identifier
        join catissue_form_record_entry re on re.form_ctxt_id = fc.identifier
        join catissue_coll_event_param cep on re.record_id = cep.identifier
      where 
        dc.name = 'SpecimenCollectionEvent' and
        fc.entity_type = 'SpecimenEvent' and 
        fc.deleted_on is null and
        re.activity_status = 'ACTIVE'
    </createView>
  </changeSet>
  
  <changeSet author="nmarwaha" id="Insert default printer site values" failOnError="false">
    <sql>
      insert into catissue_cde
        (public_id, long_name, definition, version, last_updated)
      values
        ('printer-site', 'Printer Site', 'Printer Site', '2.0', now())
    </sql>
    <sql>
      insert into catissue_permissible_value
        (identifier, value, public_id)
      values
        (default, "SGH", "printer-site")
    </sql>
    <sql>
      insert into catissue_permissible_value
        (identifier, value, public_id)
      values
        (default, "KKH", "printer-site")
    </sql>
  </changeSet>

  <changeSet author="hkambale" id="Updating quantity units for the molecular">
    <sql>
      update
        os_specimen_units
      set
        qty_unit = 'µl',
        qty_html_display_code = 'µl',
        conc_unit = 'microgram/µl',
        conc_html_display_code = 'µg/µl'
      where
        specimen_class = 'Molecular'
    </sql>
  </changeSet>

  <changeSet author="hkambale" id="Adding fat percentage column in tissue specimen event param table">
    <addColumn tableName="CATISSUE_TIS_SPE_EVENT_PARAM">
      <column name="FAT_PERCENTAGE" type="double"/>
    </addColumn>
  </changeSet>

  <changeSet author="hkambale" id="Adding columns in tissue specimen event param table">
    <addColumn tableName="CATISSUE_TIS_SPE_EVENT_PARAM">
      <column name="STROMA_PERCENTAGE" type="double"/>
      <column name="MONOCYTE_PERCENTAGE" type="double"/>
      <column name="NEUTROPHIL_PERCENTAGE" type="double"/>
    </addColumn>
  </changeSet>

  <changeSet author="hkambale" id="Updating the value for missed reason in pv table">
    <sql>
      update 
        catissue_permissible_value  
      set 
        value = 'Previous excisional biopsy done' 
      where 
        value = 'Previous excisional biospy done'
    </sql>
  </changeSet>

  <changeSet author="hkambale" id="updating the value for missed reason in visit table">
    <sql>
      update 
        catissue_specimen_coll_group
      set 
        missed_reason = 'Previous excisional biopsy done'
      where 
        missed_reason = 'Previous excisional biospy done'
    </sql>
  </changeSet>

  <changeSet author="hkambale" id="Creating visit consent available view">
    <createView viewName="os_visit_consent_avl_view" replaceIfExists="true">
      select
        user.identifier as collector_id, scg.identifier as scg_id,
        case when rntry.object_id is null then 'False' else 'True' end as consent_available
      from
        catissue_coll_prot_reg cpr
        join catissue_specimen_coll_group scg on scg.collection_protocol_reg_id = cpr.identifier
        left join catissue_specimen sp on sp.specimen_collection_group_id = scg.identifier and
        sp.collection_status = 'Collected' and
        sp.Lineage='New' and
        sp.activity_status != 'Disabled'
        left join catissue_form_record_entry record_entry on record_entry.object_id = sp.identifier and
        record_entry.form_ctxt_id = 5
        left join catissue_coll_event_param coll_event on coll_event.identifier = record_entry.record_id
        left join catissue_form_context form_context on form_context.identifier = record_entry.form_ctxt_id
        left join catissue_user user on user.identifier = coll_event.user_id
        left join catissue_form_record_entry rntry on scg.identifier=rntry.object_id and
        rntry.form_ctxt_id in ( select
                                  ctxt.identifier
                                from
                                  catissue_form_context ctxt
                                  join dyextn_containers dcont on dcont.identifier = ctxt.container_id and
                                  dcont.name = 'PatientConsentForm' and
                                  ctxt.entity_type = 'SpecimenCollectionGroup'
                              )
      where
        scg.name is not null and
        scg.activity_status != 'Disabled' and
        scg.collection_status in ('Complete','Pending')
      group by
        scg.identifier
    </createView>
  </changeSet>

</databaseChangeLog>
